{
  "@milan": {
    "username": "@milan",
    "name": "milan",
    "email": "rathodmilan422@gmail.com",
    "phone": "",
    "roll_number": "16",
    "registered_date": "2026-03-05T18:06:51.500486"
  },
  "@demonking666": {
    "username": "@demonking666",
    "name": "demonking",
    "email": "demonking@gmail.com",
    "phone": "",
    "roll_number": "13",
    "registered_date": "2026-03-09T10:38:48.612727"
  },
  "@abcc": {
    "username": "@abcc",
    "name": "abcc",
    "email": "abc@gmail.com",
    "phone": "",
    "roll_number": "786",
    "registered_date": "2026-03-09T11:03:11.100497"
  }
}